setup.py
test/test1.py
test/test2.py
wayround_org/mail/__init__.py
wayround_org/mail/datetime.py
wayround_org/mail/imap.py
wayround_org/mail/imap_search_cmd.py
wayround_org/mail/message.py
wayround_org/mail/mime.py
wayround_org/mail/miscs.py
wayround_org/mail/smtp.py
wayround_org_mail.egg-info/PKG-INFO
wayround_org_mail.egg-info/SOURCES.txt
wayround_org_mail.egg-info/dependency_links.txt
wayround_org_mail.egg-info/requires.txt
wayround_org_mail.egg-info/top_level.txt