Metadata-Version: 1.1
Name: wayround-org-mail
Version: 0.0.1
Summary: imap and smtp protocol client and server realisations. under development
Home-page: https://github.com/AnimusPEXUS/wayround_org_carafe
Author: Alexey Gorshkov
Author-email: animus@wayround.org
License: UNKNOWN
Platform: UNKNOWN
Classifier: License :: OSI Approved :: GNU General Public License v3 or later (GPLv3+)
